m3u_to_pyradio_playlist/__init__.py
m3u_to_pyradio_playlist/__main__.py
m3u_to_pyradio_playlist/converter/__init__.py
m3u_to_pyradio_playlist/converter/converter.py
m3u_to_pyradio_playlist/downloader/__init__.py
m3u_to_pyradio_playlist/downloader/downloader.py
m3u_to_pyradio_playlist/utils/__init__.py
m3u_to_pyradio_playlist/utils/utils.py
m3u_to_pyradio_playlist-0.0.4.dist-info/LICENSE
m3u_to_pyradio_playlist-0.0.4.dist-info/METADATA
m3u_to_pyradio_playlist-0.0.4.dist-info/WHEEL
m3u_to_pyradio_playlist-0.0.4.dist-info/entry_points.txt
m3u_to_pyradio_playlist-0.0.4.dist-info/top_level.txt
m3u_to_pyradio_playlist-0.0.4.dist-info/RECORD
