Metadata-Version: 2.1
Name: m3u-to-pyradio-playlist
Version: 0.0.4
Summary: Converts M3U playlists to pyradio format
Home-page: https://github.com/LionyxML/pyradio-m3u-to-playlist
Author: Rahul M. Juliato
Author-email: rahul.juliato@gmail.com
License: GPL-2.0
Platform: Any
License-File: LICENSE
Requires-Dist: requests
